the_silo/__init__.py
the_silo/logger.py
the_silo/silo_data.json
the_silo/wrapper.py
the_silo/gizmos/chromatic_abberations.gizmo
the_silo/gizmos/grade_layer.gizmo
the_silo/gizmos/refraction_diffusion.gizmo
the_silo/gizmos/vray_tonemapper.gizmo
the_silo/scripts/__init__.py
the_silo/scripts/multichannel.py
the_silo/scripts/reload.py
the_silo-0.1.2.dist-info/DESCRIPTION.rst
the_silo-0.1.2.dist-info/LICENSE.txt
the_silo-0.1.2.dist-info/METADATA
the_silo-0.1.2.dist-info/RECORD
the_silo-0.1.2.dist-info/WHEEL
the_silo-0.1.2.dist-info/metadata.json
the_silo-0.1.2.dist-info/top_level.txt
