Metadata-Version: 2.0
Name: the-silo
Version: 0.1.2
Summary: A collection of useful tools for Nuke
Home-page: https://github.com/florianeinfalt/the_silo
Author: Florian Einfalt
Author-email: info@florianeinfalt.de
License: Apache 2.0
Platform: UNKNOWN
Classifier: Development Status :: 3 - Alpha
Classifier: Intended Audience :: Developers
Classifier: Natural Language :: English
Classifier: Topic :: Software Development :: Build Tools
Classifier: License :: OSI Approved :: Apache Software License
Classifier: Programming Language :: Python
Classifier: Programming Language :: Python :: 2.6
Classifier: Programming Language :: Python :: 2.7
Classifier: Programming Language :: Python :: Implementation :: CPython
